deepgeo_ext_maskrcnn/Config.py
deepgeo_ext_maskrcnn/Dataset.py
deepgeo_ext_maskrcnn/Lib.py
deepgeo_ext_maskrcnn/Model.py
deepgeo_ext_maskrcnn/Utils.py
deepgeo_ext_maskrcnn/__init__.py
deepgeo_ext_maskrcnn-0.0.1.dist-info/LICENSE
deepgeo_ext_maskrcnn-0.0.1.dist-info/METADATA
deepgeo_ext_maskrcnn-0.0.1.dist-info/WHEEL
deepgeo_ext_maskrcnn-0.0.1.dist-info/top_level.txt
deepgeo_ext_maskrcnn-0.0.1.dist-info/RECORD
