Metadata-Version: 2.1
Name: deepgeo-ext-maskrcnn
Version: 0.0.1
Summary: deepgeo_ext_maskrcnn
Home-page: https://github.com/Sotaneum/deepgeo_ext_maskrcnn
Author: Donggun LEE
Author-email: gnyotnu39@gmail.com
License: MIT
Platform: UNKNOWN
Classifier: License :: OSI Approved :: MIT License
Requires-Dist: deepgeo (>=0.2.0)
